[
  {
    "projectName": "履歷",
    "link": "projects/resume/resume.html"
  },
  {
    "projectName": "火箭",
    "link": "projects/rocket/rocket.html"
  },
  {
    "projectName": "生日賀卡",
    "link": "projects/birthday/index.html"
  },
  {
    "projectName": "漢堡計算機",
    "link": "projects/food/index.html"
  },
  {
    "projectName": "待辦事項",
    "link": "projects/todoList/index.html"
  },
  {
    "projectName": "BMI計算ㄐ",
    "link": "projects/BMI/index.html"
  },
  {
    "projectName": "資工課表",
    "link": "projects/nutc/index.html"
  }
]